zope/dublincore/__init__.py
zope/dublincore/annotatableadapter.py
zope/dublincore/configure.zcml
zope/dublincore/creatorannotator.py
zope/dublincore/dcsv.py
zope/dublincore/dcterms.py
zope/dublincore/interfaces.py
zope/dublincore/property.py
zope/dublincore/security.zcml
zope/dublincore/testing.py
zope/dublincore/timeannotators.py
zope/dublincore/xmlmetadata.py
zope/dublincore/zopedublincore.py
zope/dublincore/browser/__init__.py
zope/dublincore/browser/box.pt
zope/dublincore/browser/configure.zcml
zope/dublincore/browser/edit.pt
zope/dublincore/browser/metadataedit.py
zope/dublincore/browser/tests/__init__.py
zope/dublincore/browser/tests/test_metadataedit.py
zope/dublincore/tests/__init__.py
zope/dublincore/tests/test_annotatableadapter.py
zope/dublincore/tests/test_creatorannotator.py
zope/dublincore/tests/test_dcsv.py
zope/dublincore/tests/test_xmlmetadata.py
zope/dublincore/tests/test_zcml.py
zope/dublincore/tests/test_zdcannotatableadapter.py
zope/dublincore/tests/test_zopedublincore.py
zope_dublincore-6.0.dist-info/licenses/LICENSE.txt
zope_dublincore-6.0.dist-info/METADATA
zope_dublincore-6.0.dist-info/WHEEL
zope_dublincore-6.0.dist-info/top_level.txt
zope_dublincore-6.0.dist-info/RECORD
