Metadata-Version: 2.4
Name: zope.dublincore
Version: 6.0
Summary: Zope Dublin Core implementation
Home-page: http://github.com/zopefoundation/zope.dublincore
Author: Zope Foundation and Contributors
Author-email: zope-dev@zope.dev
License: ZPL-2.1
Keywords: metadata dublincore
Classifier: Development Status :: 5 - Production/Stable
Classifier: Intended Audience :: Developers
Classifier: License :: OSI Approved :: Zope Public License
Classifier: Natural Language :: English
Classifier: Operating System :: OS Independent
Classifier: Programming Language :: Python
Classifier: Programming Language :: Python :: 3
Classifier: Programming Language :: Python :: 3.9
Classifier: Programming Language :: Python :: 3.10
Classifier: Programming Language :: Python :: 3.11
Classifier: Programming Language :: Python :: 3.12
Classifier: Programming Language :: Python :: 3.13
Classifier: Programming Language :: Python :: Implementation :: CPython
Classifier: Programming Language :: Python :: Implementation :: PyPy
Classifier: Topic :: Internet :: WWW/HTTP
Classifier: Topic :: Software Development
Requires-Python: >=3.9
License-File: LICENSE.txt
Requires-Dist: persistent
Requires-Dist: pytz
Requires-Dist: setuptools
Requires-Dist: zope.annotation
Requires-Dist: zope.component[zcml]
Requires-Dist: zope.datetime
Requires-Dist: zope.interface
Requires-Dist: zope.lifecycleevent
Requires-Dist: zope.location
Requires-Dist: zope.schema
Requires-Dist: zope.security[zcml]>=3.8
Provides-Extra: testing
Requires-Dist: zope.testing>=3.8; extra == "testing"
Requires-Dist: zope.testrunner>=6.4; extra == "testing"
Requires-Dist: zope.configuration; extra == "testing"
Requires-Dist: BTrees; extra == "testing"
Provides-Extra: test
Requires-Dist: zope.testing>=3.8; extra == "test"
Requires-Dist: zope.testrunner>=6.4; extra == "test"
Requires-Dist: zope.configuration; extra == "test"
Requires-Dist: BTrees; extra == "test"
Requires-Dist: zope.publisher; extra == "test"
Provides-Extra: docs
Requires-Dist: Sphinx; extra == "docs"
Requires-Dist: repoze.sphinx.autointerface; extra == "docs"
Requires-Dist: zope.testing; extra == "docs"
Dynamic: author
Dynamic: author-email
Dynamic: classifier
Dynamic: description
Dynamic: home-page
Dynamic: keywords
Dynamic: license
Dynamic: license-file
Dynamic: provides-extra
Dynamic: requires-dist
Dynamic: requires-python
Dynamic: summary
